firefly_aws/__init__.py
firefly_aws/application/__init__.py
firefly_aws/application/container.py
firefly_aws/application/authentication/__init__.py
firefly_aws/application/authentication/cognito_authenticator.py
firefly_aws/application/middleware/__init__.py
firefly_aws/application/middleware/adaptive_memory_routing_middleware.py
firefly_aws/application/middleware/authenticating_middleware.py
firefly_aws/application/middleware/resource_monitoring_middleware.py
firefly_aws/application/service/__init__.py
firefly_aws/application/service/aws_agent.py
firefly_aws/application/service/process_error.py
firefly_aws/application/service/update_resource_settings.py
firefly_aws/domain/__init__.py
firefly_aws/domain/error.py
firefly_aws/domain/resource_name_aware.py
firefly_aws/domain/entity/__init__.py
firefly_aws/domain/entity/project.py
firefly_aws/domain/entity/service.py
firefly_aws/domain/entity/stack.py
firefly_aws/domain/service/__init__.py
firefly_aws/domain/service/ddb_serializer.py
firefly_aws/domain/service/execution_context.py
firefly_aws/domain/service/find_outlier_threshold.py
firefly_aws/domain/service/handle_error.py
firefly_aws/domain/service/jwt_decoder.py
firefly_aws/domain/service/lambda_executor.py
firefly_aws/domain/service/load_payload.py
firefly_aws/domain/service/prepare_s3_download.py
firefly_aws/domain/service/requeue_message.py
firefly_aws/domain/service/resource_monitor.py
firefly_aws/domain/service/s3_service.py
firefly_aws/domain/service/store_large_payloads_in_s3.py
firefly_aws/infrastructure/__init__.py
firefly_aws/infrastructure/repository/__init__.py
firefly_aws/infrastructure/repository/data_api_mysql_mapped_storage_interface.py
firefly_aws/infrastructure/repository/data_api_mysql_storage_interface.py
firefly_aws/infrastructure/repository/data_api_storage_interface.py
firefly_aws/infrastructure/repository/s3_connection_factory.py
firefly_aws/infrastructure/repository/s3_repository.py
firefly_aws-1.2.15.dist-info/LICENSE
firefly_aws-1.2.15.dist-info/METADATA
firefly_aws-1.2.15.dist-info/WHEEL
firefly_aws-1.2.15.dist-info/entry_points.txt
firefly_aws-1.2.15.dist-info/top_level.txt
firefly_aws-1.2.15.dist-info/RECORD
