Metadata-Version: 2.1
Name: firefly-aws
Version: 1.2.15
Summary: AWS extension for the Firefly framework.
Home-page: 
Author: 
Author-email: 
Classifier: Programming Language :: Python :: 3.7
Classifier: Operating System :: OS Independent
License-File: LICENSE
Requires-Dist: boto3 (>=1.12.42)
Requires-Dist: cognitojwt (>=1.2.2)
Requires-Dist: dateparser (>=0.7.4)
Requires-Dist: dynamodb-json (>=1.3)
Requires-Dist: firefly-dependency-injection (>=1.0.0)
Requires-Dist: firefly-framework (>=1.2.4)
Requires-Dist: Jinja2 (>=2.11.1)
Requires-Dist: jinjasql (>=0.1.8)
Requires-Dist: multipart (>=0.2.3)
Requires-Dist: psutil (>=5.8.0)
Requires-Dist: requests (>=2.23.0)
Requires-Dist: troposphere (>=2.7.1)
